[
    {
        "parent": "C:\\Users\\kitti\\OneDrive\\\u0420\u0430\u0431\u043e\u0447\u0438\u0439 \u0441\u0442\u043e\u043b\\\u0440\u0430\u0437\u0440\u0430\u0431\u043e\u0442\u0447\u0438\u043a\\tester\\python\\seminar8",
        "type": "file",
        "name": "result.csv",
        "size": 5302
    },
    {
        "parent": "C:\\Users\\kitti\\OneDrive\\\u0420\u0430\u0431\u043e\u0447\u0438\u0439 \u0441\u0442\u043e\u043b\\\u0440\u0430\u0437\u0440\u0430\u0431\u043e\u0442\u0447\u0438\u043a\\tester\\python\\seminar8",
        "type": "file",
        "name": "result.json",
        "size": 15868
    },
    {
        "parent": "C:\\Users\\kitti\\OneDrive\\\u0420\u0430\u0431\u043e\u0447\u0438\u0439 \u0441\u0442\u043e\u043b\\\u0440\u0430\u0437\u0440\u0430\u0431\u043e\u0442\u0447\u0438\u043a\\tester\\python\\seminar8",
        "type": "file",
        "name": "results.pkl",
        "size": 2825
    },
    {
        "parent": "C:\\Users\\kitti\\OneDrive\\\u0420\u0430\u0431\u043e\u0447\u0438\u0439 \u0441\u0442\u043e\u043b\\\u0440\u0430\u0437\u0440\u0430\u0431\u043e\u0442\u0447\u0438\u043a\\tester\\python\\seminar8",
        "type": "file",
        "name": "results.txt",
        "size": 308
    },
    {
        "parent": "C:\\Users\\kitti\\OneDrive\\\u0420\u0430\u0431\u043e\u0447\u0438\u0439 \u0441\u0442\u043e\u043b\\\u0440\u0430\u0437\u0440\u0430\u0431\u043e\u0442\u0447\u0438\u043a\\tester\\python\\seminar8",
        "type": "file",
        "name": "task1.py",
        "size": 2771
    },
    {
        "parent": "C:\\Users\\kitti\\OneDrive\\\u0420\u0430\u0431\u043e\u0447\u0438\u0439 \u0441\u0442\u043e\u043b\\\u0440\u0430\u0437\u0440\u0430\u0431\u043e\u0442\u0447\u0438\u043a\\tester\\python\\seminar8",
        "type": "file",
        "name": "Task1_Home8.py",
        "size": 2415
    }
]